asimov/__init__.py
asimov/__init__.pyc
asimov/asimov.conf
asimov/condor.py
asimov/event.py
asimov/git.py
asimov/gitlab.py
asimov/ini.py
asimov/ledger.py
asimov/locutus.py
asimov/logging.py
asimov/mattermost.py
asimov/olivaw.py
asimov/pipeline.py
asimov/review.py
asimov/storage.py
asimov/testing.py
asimov/cli/__init__.py
asimov/cli/config.py
asimov/cli/configuration.py
asimov/cli/data.py
asimov/cli/event.py
asimov/cli/ledger.py
asimov/cli/manage.py
asimov/cli/monitor.py
asimov/cli/production.py
asimov/cli/project.py
asimov/cli/report.py
asimov/cli/review.py
asimov/configs/README.rst
asimov/configs/bayeswave.ini
asimov/configs/bilby.ini
asimov/configs/lalinference.ini
asimov/configs/rift.ini
asimov/pipelines/__init__.py
asimov/pipelines/bayeswave.py
asimov/pipelines/bilby.py
asimov/pipelines/lalinference.py
asimov/pipelines/rift.py
asimov/priors/bbh.prior.template
ligo_asimov-0.3.3.dist-info/LICENSE
ligo_asimov-0.3.3.dist-info/METADATA
ligo_asimov-0.3.3.dist-info/WHEEL
ligo_asimov-0.3.3.dist-info/entry_points.txt
ligo_asimov-0.3.3.dist-info/top_level.txt
ligo_asimov-0.3.3.dist-info/zip-safe
ligo_asimov-0.3.3.dist-info/RECORD
